[ {
  "id" : "620556",
  "name" : "Cent Wallpaper",
  "resolution" : "1024x768",
  "tag" : "50-cent",
  "dataUrl" : "/full/620556.jpg",
  "downloadUrl" : "/download/50-cent-620556",
  "dataSource" : "https://wallpaperaccess.com/full/620556.jpg",
  "downloadSource" : "https://wallpaperaccess.com/download/50-cent-620556"
}, {
  "id" : "1672983",
  "name" : "Cent Wallpaper",
  "resolution" : "1920x1080",
  "tag" : "50-cent",
  "dataUrl" : "/full/1672983.jpg",
  "downloadUrl" : "/download/50-cent-1672983",
  "dataSource" : "https://wallpaperaccess.com/full/1672983.jpg",
  "downloadSource" : "https://wallpaperaccess.com/download/50-cent-1672983"
}, {
  "id" : "620562",
  "name" : "Cents Wallpaper",
  "resolution" : "1280x1024",
  "tag" : "50-cent",
  "dataUrl" : "/full/620562.jpg",
  "downloadUrl" : "/download/50-cent-620562",
  "dataSource" : "https://wallpaperaccess.com/full/620562.jpg",
  "downloadSource" : "https://wallpaperaccess.com/download/50-cent-620562"
}, {
  "id" : "620624",
  "name" : "Cent Wallpaper 2015",
  "resolution" : "1920x1080",
  "tag" : "50-cent",
  "dataUrl" : "/full/620624.jpg",
  "downloadUrl" : "/download/50-cent-620624",
  "dataSource" : "https://wallpaperaccess.com/full/620624.jpg",
  "downloadSource" : "https://wallpaperaccess.com/download/50-cent-620624"
}, {
  "id" : "620579",
  "name" : "Cent Wallpaper 2016",
  "resolution" : "1600x1200",
  "tag" : "50-cent",
  "dataUrl" : "/full/620579.jpg",
  "downloadUrl" : "/download/50-cent-620579",
  "dataSource" : "https://wallpaperaccess.com/full/620579.jpg",
  "downloadSource" : "https://wallpaperaccess.com/download/50-cent-620579"
}, {
  "id" : "620536",
  "name" : "Cent Wallpaper and Background Image",
  "resolution" : "1366x768",
  "tag" : "50-cent",
  "dataUrl" : "/full/620536.jpg",
  "downloadUrl" : "/download/50-cent-620536",
  "dataSource" : "https://wallpaperaccess.com/full/620536.jpg",
  "downloadSource" : "https://wallpaperaccess.com/download/50-cent-620536"
}, {
  "id" : "1672987",
  "name" : "50Cent♥ - 50 Cent Wallpaper",
  "resolution" : "1280x1024",
  "tag" : "50-cent",
  "dataUrl" : "/full/1672987.jpg",
  "downloadUrl" : "/download/50-cent-1672987",
  "dataSource" : "https://wallpaperaccess.com/full/1672987.jpg",
  "downloadSource" : "https://wallpaperaccess.com/download/50-cent-1672987"
}, {
  "id" : "1672988",
  "name" : "picture of 50 cent. 50 Cent Wallpaper",
  "resolution" : "1280x1024",
  "tag" : "50-cent",
  "dataUrl" : "/full/1672988.jpg",
  "downloadUrl" : "/download/50-cent-1672988",
  "dataSource" : "https://wallpaperaccess.com/full/1672988.jpg",
  "downloadSource" : "https://wallpaperaccess.com/download/50-cent-1672988"
}, {
  "id" : "1672989",
  "name" : "Cent Desktop Wallpaper Desktop Wallpaper High Definition",
  "resolution" : "2800x2100",
  "tag" : "50-cent",
  "dataUrl" : "/full/1672989.jpg",
  "downloadUrl" : "/download/50-cent-1672989",
  "dataSource" : "https://wallpaperaccess.com/full/1672989.jpg",
  "downloadSource" : "https://wallpaperaccess.com/download/50-cent-1672989"
}, {
  "id" : "1672991",
  "name" : "Nice 50 Cent Wallpaper HD 4k High Definition Windows 10 Mac",
  "resolution" : "1920x1080",
  "tag" : "50-cent",
  "dataUrl" : "/full/1672991.jpg",
  "downloadUrl" : "/download/50-cent-1672991",
  "dataSource" : "https://wallpaperaccess.com/full/1672991.jpg",
  "downloadSource" : "https://wallpaperaccess.com/download/50-cent-1672991"
}, {
  "id" : "1672992",
  "name" : "Cent Wallpaper",
  "resolution" : "1280x1024",
  "tag" : "50-cent",
  "dataUrl" : "/full/1672992.jpg",
  "downloadUrl" : "/download/50-cent-1672992",
  "dataSource" : "https://wallpaperaccess.com/full/1672992.jpg",
  "downloadSource" : "https://wallpaperaccess.com/download/50-cent-1672992"
}, {
  "id" : "620545",
  "name" : "Cent Wallpaper",
  "resolution" : "1024x768",
  "tag" : "50-cent",
  "dataUrl" : "/full/620545.jpg",
  "downloadUrl" : "/download/50-cent-620545",
  "dataSource" : "https://wallpaperaccess.com/full/620545.jpg",
  "downloadSource" : "https://wallpaperaccess.com/download/50-cent-620545"
}, {
  "id" : "1672994",
  "name" : "50 Cent HD Wallpaper and Background Image",
  "resolution" : "1920x1200",
  "tag" : "50-cent",
  "dataUrl" : "/full/1672994.jpg",
  "downloadUrl" : "/download/50-cent-1672994",
  "dataSource" : "https://wallpaperaccess.com/full/1672994.jpg",
  "downloadSource" : "https://wallpaperaccess.com/download/50-cent-1672994"
}, {
  "id" : "1672995",
  "name" : "Cent Wallpaper 20 - 1024 X 768",
  "resolution" : "1024x768",
  "tag" : "50-cent",
  "dataUrl" : "/full/1672995.jpg",
  "downloadUrl" : "/download/50-cent-1672995",
  "dataSource" : "https://wallpaperaccess.com/full/1672995.jpg",
  "downloadSource" : "https://wallpaperaccess.com/download/50-cent-1672995"
}, {
  "id" : "1672996",
  "name" : "Cent Wallpaper Widescreen O1WQ",
  "resolution" : "1680x1050",
  "tag" : "50-cent",
  "dataUrl" : "/full/1672996.jpg",
  "downloadUrl" : "/download/50-cent-1672996",
  "dataSource" : "https://wallpaperaccess.com/full/1672996.jpg",
  "downloadSource" : "https://wallpaperaccess.com/download/50-cent-1672996"
}, {
  "id" : "1672997",
  "name" : "cent and tony yayo. unit wallpaper, 50 cent, lloyd banks",
  "resolution" : "1920x1200",
  "tag" : "50-cent",
  "dataUrl" : "/full/1672997.jpg",
  "downloadUrl" : "/download/50-cent-1672997",
  "dataSource" : "https://wallpaperaccess.com/full/1672997.jpg",
  "downloadSource" : "https://wallpaperaccess.com/download/50-cent-1672997"
}, {
  "id" : "287328",
  "name" : "Cent, 50 Cent Bulletproof, 50 Cent Bulletproof Game",
  "resolution" : "2560x1600",
  "tag" : "50-cent",
  "dataUrl" : "/full/287328.jpg",
  "downloadUrl" : "/download/50-cent-287328",
  "dataSource" : "https://wallpaperaccess.com/full/287328.jpg",
  "downloadSource" : "https://wallpaperaccess.com/download/50-cent-287328"
}, {
  "id" : "1672998",
  "name" : "Cent Wallpaper 16 - 5500 X 4125",
  "resolution" : "5500x4125",
  "tag" : "50-cent",
  "dataUrl" : "/full/1672998.jpg",
  "downloadUrl" : "/download/50-cent-1672998",
  "dataSource" : "https://wallpaperaccess.com/full/1672998.jpg",
  "downloadSource" : "https://wallpaperaccess.com/download/50-cent-1672998"
}, {
  "id" : "1672999",
  "name" : "50 Cent Wallpaper 2015",
  "resolution" : "930x1395",
  "tag" : "50-cent",
  "dataUrl" : "/full/1672999.jpg",
  "downloadUrl" : "/download/50-cent-1672999",
  "dataSource" : "https://wallpaperaccess.com/full/1672999.jpg",
  "downloadSource" : "https://wallpaperaccess.com/download/50-cent-1672999"
}, {
  "id" : "1673000",
  "name" : "Cent Wallpaper Download #XMI527X",
  "resolution" : "1920x1080",
  "tag" : "50-cent",
  "dataUrl" : "/full/1673000.jpg",
  "downloadUrl" : "/download/50-cent-1673000",
  "dataSource" : "https://wallpaperaccess.com/full/1673000.jpg",
  "downloadSource" : "https://wallpaperaccess.com/download/50-cent-1673000"
}, {
  "id" : "620567",
  "name" : "Best HD 50 Cent Wallpaper",
  "resolution" : "1680x1259",
  "tag" : "50-cent",
  "dataUrl" : "/full/620567.jpg",
  "downloadUrl" : "/download/50-cent-620567",
  "dataSource" : "https://wallpaperaccess.com/full/620567.jpg",
  "downloadSource" : "https://wallpaperaccess.com/download/50-cent-620567"
}, {
  "id" : "1673002",
  "name" : "50 Cent Wallpaper Free Download",
  "resolution" : "1024x768",
  "tag" : "50-cent",
  "dataUrl" : "/full/1673002.jpg",
  "downloadUrl" : "/download/50-cent-1673002",
  "dataSource" : "https://wallpaperaccess.com/full/1673002.jpg",
  "downloadSource" : "https://wallpaperaccess.com/download/50-cent-1673002"
}, {
  "id" : "1673003",
  "name" : "Cent Wallpaper 24 - 1024 X 768",
  "resolution" : "1024x768",
  "tag" : "50-cent",
  "dataUrl" : "/full/1673003.jpg",
  "downloadUrl" : "/download/50-cent-1673003",
  "dataSource" : "https://wallpaperaccess.com/full/1673003.jpg",
  "downloadSource" : "https://wallpaperaccess.com/download/50-cent-1673003"
}, {
  "id" : "1673004",
  "name" : "Cent 3 - BANDSWALLPAPERS. free wallpaper, music",
  "resolution" : "1024x768",
  "tag" : "50-cent",
  "dataUrl" : "/full/1673004.jpg",
  "downloadUrl" : "/download/50-cent-1673004",
  "dataSource" : "https://wallpaperaccess.com/full/1673004.jpg",
  "downloadSource" : "https://wallpaperaccess.com/download/50-cent-1673004"
}, {
  "id" : "449002",
  "name" : "Cent Wallpaper",
  "resolution" : "1024x768",
  "tag" : "50-cent",
  "dataUrl" : "/full/449002.jpg",
  "downloadUrl" : "/download/50-cent-449002",
  "dataSource" : "https://wallpaperaccess.com/full/449002.jpg",
  "downloadSource" : "https://wallpaperaccess.com/download/50-cent-449002"
}, {
  "id" : "1673006",
  "name" : "Cent Wallpaper and Background Image",
  "resolution" : "1600x1200",
  "tag" : "50-cent",
  "dataUrl" : "/full/1673006.jpg",
  "downloadUrl" : "/download/50-cent-1673006",
  "dataSource" : "https://wallpaperaccess.com/full/1673006.jpg",
  "downloadSource" : "https://wallpaperaccess.com/download/50-cent-1673006"
}, {
  "id" : "1673007",
  "name" : "Cent Wallpaper – WeNeedFun",
  "resolution" : "1265x766",
  "tag" : "50-cent",
  "dataUrl" : "/full/1673007.jpg",
  "downloadUrl" : "/download/50-cent-1673007",
  "dataSource" : "https://wallpaperaccess.com/full/1673007.jpg",
  "downloadSource" : "https://wallpaperaccess.com/download/50-cent-1673007"
}, {
  "id" : "1673009",
  "name" : "Wallpaper wave, abstraction, the city, music, rap, rapper",
  "resolution" : "1332x850",
  "tag" : "50-cent",
  "dataUrl" : "/full/1673009.jpg",
  "downloadUrl" : "/download/50-cent-1673009",
  "dataSource" : "https://wallpaperaccess.com/full/1673009.jpg",
  "downloadSource" : "https://wallpaperaccess.com/download/50-cent-1673009"
}, {
  "id" : "1673010",
  "name" : "Cent Actor Wallpaper Background 58984 4256x2832px",
  "resolution" : "4256x2832",
  "tag" : "50-cent",
  "dataUrl" : "/full/1673010.jpg",
  "downloadUrl" : "/download/50-cent-1673010",
  "dataSource" : "https://wallpaperaccess.com/full/1673010.jpg",
  "downloadSource" : "https://wallpaperaccess.com/download/50-cent-1673010"
}, {
  "id" : "1673011",
  "name" : "Picture 50 Cent Music",
  "resolution" : "1024x768",
  "tag" : "50-cent",
  "dataUrl" : "/full/1673011.jpg",
  "downloadUrl" : "/download/50-cent-1673011",
  "dataSource" : "https://wallpaperaccess.com/full/1673011.jpg",
  "downloadSource" : "https://wallpaperaccess.com/download/50-cent-1673011"
}, {
  "id" : "1673012",
  "name" : "Cent Wallpaper Desktop px",
  "resolution" : "1280x960",
  "tag" : "50-cent",
  "dataUrl" : "/full/1673012.png",
  "downloadUrl" : "/download/50-cent-1673012",
  "dataSource" : "https://wallpaperaccess.com/full/1673012.png",
  "downloadSource" : "https://wallpaperaccess.com/download/50-cent-1673012"
}, {
  "id" : "1673013",
  "name" : "Eminem And 50 Cent Wallpaper",
  "resolution" : "1600x1200",
  "tag" : "50-cent",
  "dataUrl" : "/full/1673013.jpg",
  "downloadUrl" : "/download/50-cent-1673013",
  "dataSource" : "https://wallpaperaccess.com/full/1673013.jpg",
  "downloadSource" : "https://wallpaperaccess.com/download/50-cent-1673013"
}, {
  "id" : "1673014",
  "name" : "Cent Wallpaper 21 - 1366 X 768",
  "resolution" : "1366x768",
  "tag" : "50-cent",
  "dataUrl" : "/full/1673014.jpg",
  "downloadUrl" : "/download/50-cent-1673014",
  "dataSource" : "https://wallpaperaccess.com/full/1673014.jpg",
  "downloadSource" : "https://wallpaperaccess.com/download/50-cent-1673014"
}, {
  "id" : "1673015",
  "name" : "Cent Wallpaper 12 - 1920 X 1080",
  "resolution" : "1920x1080",
  "tag" : "50-cent",
  "dataUrl" : "/full/1673015.jpg",
  "downloadUrl" : "/download/50-cent-1673015",
  "dataSource" : "https://wallpaperaccess.com/full/1673015.jpg",
  "downloadSource" : "https://wallpaperaccess.com/download/50-cent-1673015"
}, {
  "id" : "1673016",
  "name" : "50Cent♥ - 50 Cent Wallpaper",
  "resolution" : "1280x1024",
  "tag" : "50-cent",
  "dataUrl" : "/full/1673016.jpg",
  "downloadUrl" : "/download/50-cent-1673016",
  "dataSource" : "https://wallpaperaccess.com/full/1673016.jpg",
  "downloadSource" : "https://wallpaperaccess.com/download/50-cent-1673016"
}, {
  "id" : "287339",
  "name" : "Cent Wallpaper",
  "resolution" : "1024x768",
  "tag" : "50-cent",
  "dataUrl" : "/full/287339.jpg",
  "downloadUrl" : "/download/50-cent-287339",
  "dataSource" : "https://wallpaperaccess.com/full/287339.jpg",
  "downloadSource" : "https://wallpaperaccess.com/download/50-cent-287339"
}, {
  "id" : "1673018",
  "name" : "iPhone 6 50 Cent Wallpaper HD, Desktop Background 750x1334",
  "resolution" : "750x1334",
  "tag" : "50-cent",
  "dataUrl" : "/full/1673018.jpg",
  "downloadUrl" : "/download/50-cent-1673018",
  "dataSource" : "https://wallpaperaccess.com/full/1673018.jpg",
  "downloadSource" : "https://wallpaperaccess.com/download/50-cent-1673018"
}, {
  "id" : "1519792",
  "name" : "G Unit Wallpaper",
  "resolution" : "1920x1080",
  "tag" : "50-cent",
  "dataUrl" : "/full/1519792.jpg",
  "downloadUrl" : "/download/50-cent-1519792",
  "dataSource" : "https://wallpaperaccess.com/full/1519792.jpg",
  "downloadSource" : "https://wallpaperaccess.com/download/50-cent-1519792"
}, {
  "id" : "1673020",
  "name" : "Cent Wallpaper 2018",
  "resolution" : "1920x1080",
  "tag" : "50-cent",
  "dataUrl" : "/full/1673020.jpg",
  "downloadUrl" : "/download/50-cent-1673020",
  "dataSource" : "https://wallpaperaccess.com/full/1673020.jpg",
  "downloadSource" : "https://wallpaperaccess.com/download/50-cent-1673020"
}, {
  "id" : "1673023",
  "name" : "Cent Wallpaper Download Free Desktop Wallpaper High",
  "resolution" : "3600x2480",
  "tag" : "50-cent",
  "dataUrl" : "/full/1673023.jpg",
  "downloadUrl" : "/download/50-cent-1673023",
  "dataSource" : "https://wallpaperaccess.com/full/1673023.jpg",
  "downloadSource" : "https://wallpaperaccess.com/download/50-cent-1673023"
}, {
  "id" : "1673024",
  "name" : "Cent Wallpaper R2P9Q",
  "resolution" : "771x1036",
  "tag" : "50-cent",
  "dataUrl" : "/full/1673024.png",
  "downloadUrl" : "/download/50-cent-1673024",
  "dataSource" : "https://wallpaperaccess.com/full/1673024.png",
  "downloadSource" : "https://wallpaperaccess.com/download/50-cent-1673024"
}, {
  "id" : "1673025",
  "name" : "Cent Wallpaper",
  "resolution" : "1920x1080",
  "tag" : "50-cent",
  "dataUrl" : "/full/1673025.jpg",
  "downloadUrl" : "/download/50-cent-1673025",
  "dataSource" : "https://wallpaperaccess.com/full/1673025.jpg",
  "downloadSource" : "https://wallpaperaccess.com/download/50-cent-1673025"
}, {
  "id" : "1673026",
  "name" : "Cent",
  "resolution" : "1280x960",
  "tag" : "50-cent",
  "dataUrl" : "/full/1673026.jpg",
  "downloadUrl" : "/download/50-cent-1673026",
  "dataSource" : "https://wallpaperaccess.com/full/1673026.jpg",
  "downloadSource" : "https://wallpaperaccess.com/download/50-cent-1673026"
}, {
  "id" : "1673027",
  "name" : "CENT Curtis Jackson Hip Hop Rap Cent Gangsta A Wallpaper",
  "resolution" : "1920x1200",
  "tag" : "50-cent",
  "dataUrl" : "/full/1673027.jpg",
  "downloadUrl" : "/download/50-cent-1673027",
  "dataSource" : "https://wallpaperaccess.com/full/1673027.jpg",
  "downloadSource" : "https://wallpaperaccess.com/download/50-cent-1673027"
}, {
  "id" : "1673028",
  "name" : "Cent Wallpaper 9 - 2000 X 1331",
  "resolution" : "2000x1331",
  "tag" : "50-cent",
  "dataUrl" : "/full/1673028.jpg",
  "downloadUrl" : "/download/50-cent-1673028",
  "dataSource" : "https://wallpaperaccess.com/full/1673028.jpg",
  "downloadSource" : "https://wallpaperaccess.com/download/50-cent-1673028"
}, {
  "id" : "1673029",
  "name" : "Cent wallpaper desktop background",
  "resolution" : "1440x900",
  "tag" : "50-cent",
  "dataUrl" : "/full/1673029.jpg",
  "downloadUrl" : "/download/50-cent-1673029",
  "dataSource" : "https://wallpaperaccess.com/full/1673029.jpg",
  "downloadSource" : "https://wallpaperaccess.com/download/50-cent-1673029"
}, {
  "id" : "1673031",
  "name" : "Image 50 Cent Music",
  "resolution" : "1280x1024",
  "tag" : "50-cent",
  "dataUrl" : "/full/1673031.jpg",
  "downloadUrl" : "/download/50-cent-1673031",
  "dataSource" : "https://wallpaperaccess.com/full/1673031.jpg",
  "downloadSource" : "https://wallpaperaccess.com/download/50-cent-1673031"
} ]